{
  "kind": "singleType",
  "collectionName": "layouts",
  "info": {
    "singularName": "layout",
    "pluralName": "layouts",
    "displayName": "Layout",
    "description": ""
  },
  "options": {
    "draftAndPublish": true
  },
  "pluginOptions": {
    "i18n": {
      "localized": true
    }
  },
  "attributes": {
    "header": {
      "displayName": "Header",
      "type": "component",
      "repeatable": false,
      "component": "ui.header",
      "pluginOptions": {
        "i18n": {
          "localized": true
        }
      }
    },
    "footer": {
      "displayName": "footer",
      "type": "component",
      "repeatable": false,
      "pluginOptions": {
        "i18n": {
          "localized": true
        }
      },
      "component": "ui.footer"
    }
  }
}
